qyin.py
qyin-0.1.0.dist-info/LICENSE
qyin-0.1.0.dist-info/METADATA
qyin-0.1.0.dist-info/WHEEL
qyin-0.1.0.dist-info/RECORD
